README
setup.py
poll/__init__.py
poll/admin.py
poll/models.py
poll/tasks.py
poll/tests.py
poll/views.py
test_poll_project.egg-info/PKG-INFO
test_poll_project.egg-info/SOURCES.txt
test_poll_project.egg-info/dependency_links.txt
test_poll_project.egg-info/top_level.txt