Metadata-Version: 1.1
Name: test-poll-project
Version: 0.8
Summary: test project for poll
Home-page: http://packages.python.org/an_example_pypi_project
Author: Mahesh Lagadapati
Author-email: mlagada@ncsu.edu
License: BSD
Keywords: test poll
Platform: UNKNOWN
Classifier: Development Status :: 3 - Alpha
Classifier: Topic :: Utilities
Classifier: License :: OSI Approved :: BSD License
